cmdtools/__init__.py
cmdtools/utils.py
cmdtools/analysis/__init__.py
cmdtools/analysis/optimization.py
cmdtools/analysis/pcca.py
cmdtools/analysis/schur.py
cmdtools/estimation/__init__.py
cmdtools/estimation/ajc.py
cmdtools/estimation/diffusionmaps.py
cmdtools/estimation/galerkin.py
cmdtools/estimation/gillespie.py
cmdtools/estimation/newton_generator.py
cmdtools/estimation/picking_algorithm.py
cmdtools/estimation/sqra.py
cmdtools/estimation/voronoi.py
cmdtools/systems/__init__.py
cmdtools/systems/diffusion.py
cmdtools-1.0.2.dist-info/METADATA
cmdtools-1.0.2.dist-info/WHEEL
cmdtools-1.0.2.dist-info/top_level.txt
cmdtools-1.0.2.dist-info/RECORD
