Metadata-Version: 2.1
Name: cmdtools
Version: 1.0.2
Summary: A collection of tools relating to transfer operators
Home-page: https://github.com/zib-cmd/cmdtools
Author: Alexander Sikorski
Author-email: sikorski@zib.de
Classifier: Programming Language :: Python :: 3
Classifier: Operating System :: OS Independent
Requires-Dist: numpy
Requires-Dist: scipy
Requires-Dist: scikit-learn
Provides-Extra: slepc
Requires-Dist: slepc4py; extra == "slepc"
Provides-Extra: tests
Requires-Dist: pytest; extra == "tests"
Requires-Dist: pytest-cov; extra == "tests"
Requires-Dist: pytest-benchmark; extra == "tests"
